utils_seq/__init__.py
utils_seq/__main__.py
utils_seq/_run.py
utils_seq-0.1.2.dist-info/LICENSE.txt
utils_seq-0.1.2.dist-info/METADATA
utils_seq-0.1.2.dist-info/WHEEL
utils_seq-0.1.2.dist-info/top_level.txt
utils_seq-0.1.2.dist-info/RECORD
