Metadata-Version: 2.1
Name: utils_seq
Version: 0.1.2
Summary: simple utils for seqs
Author-email: Johannes <johannes-programming@mailfence.com>, Johannes <johannes-programming@posteo.org>
License: The MIT License (MIT)
Project-URL: Documentation, https://pypi.org/project/utils_seq
Project-URL: Download, https://pypi.org/project/utils-seq/#files
Project-URL: Source, https://github.com/johannes-programming/utils_seq
Classifier: License :: OSI Approved :: MIT License
Classifier: Programming Language :: Python
Classifier: Programming Language :: Python :: 3
Classifier: Programming Language :: Python :: 3 :: Only
Requires-Python: >=3.11
License-File: LICENSE.txt
Requires-Dist: Bio >=1.6
Requires-Dist: gravy >=1.0
Requires-Dist: seqpad >=1.0
Requires-Dist: wonderparse >=1.0
